SQLSimplify/__init__.py
SQLSimplify/sqlsimplify.py
SQLSimplify/test.py
SQLSimplify-0.1.dist-info/LICENSE
SQLSimplify-0.1.dist-info/METADATA
SQLSimplify-0.1.dist-info/WHEEL
SQLSimplify-0.1.dist-info/top_level.txt
SQLSimplify-0.1.dist-info/RECORD
