Metadata-Version: 2.1
Name: SQLSimplify
Version: 0.1
Summary: A Python library for easy SQl operations
Author-email: Ankush Kumar <ankush1611996@gmail.com>
Project-URL: Homepage, https://github.com/AnkushRozra/quicksql
Project-URL: Bug Tracker, https://github.com/AnkushRozra/quicksql/issues
Keywords: pysql,sqlite,python sql,quicksql,sql,mysql,SQLSimplify
Classifier: Programming Language :: Python :: 3
Classifier: License :: OSI Approved :: MIT License
Classifier: Operating System :: OS Independent
Requires-Python: >=3.8
License-File: LICENSE
Requires-Dist: mysql-connector-python
